{
    "map": {},
    "extends": [],
    "generated": {
        "map": {
            "@coffeekraken.s-deps-feature.js.interface.SDepsFeatureInterface": {
                "id": "@coffeekraken.s-deps-feature.js.interface.SDepsFeatureInterface",
                "name": "SDepsFeatureInterface",
                "type": {
                    "types": [
                        {
                            "type": "Class"
                        }
                    ],
                    "raw": "Class"
                },
                "platform": [
                    {
                        "name": "js",
                        "description": ""
                    }
                ],
                "description": "This interface represent the attributes of the SCssPartial feature",
                "namespace": "@coffeekraken.s-deps-feature.js.interface",
                "status": "beta",
                "interface": {
                    "name": "SDepsFeatureInterface",
                    "description": "",
                    "definition": {
                        "css": {
                            "type": {
                                "types": [
                                    {
                                        "type": "String"
                                    }
                                ],
                                "raw": "String"
                            },
                            "description": "Specify the \"partial\" css you want to load. This is relative to the \"rootPath\" property and can be a simple id like \"welcome\" that will resolve to \"${cssPartialsPath}/welcome.css\" or directly a path"
                        }
                    }
                },
                "since": "2.0.0",
                "author": {
                    "name": "Olivier Bossel",
                    "email": "olivier.bossel@gmail.com",
                    "url": "https://coffeekraken.io"
                },
                "filename": "SDepsFeatureInterface.ts",
                "extension": "ts",
                "relPath": "src/js/interface/SDepsFeatureInterface.ts",
                "children": {}
            }
        }
    }
}