{
    "type": "Object{}",
    "description": "Specify the margins you want around your layout",
    "props": {
        "block": {
            "extends": "sugar.views.props.space",
            "description": "Specify the margin block (top, bottom)"
        },
        "inline": {
            "extends": "sugar.views.props.space",
            "description": "Specify the margin inkine (left, right)"
        },
        "blockStart": {
            "extends": "sugar.views.props.space",
            "description": "Specify the margin block start (top)"
        },
        "blockEnd": {
            "extends": "sugar.views.props.space",
            "description": "Specify the margin block end (bottom)"
        },
        "inlineStart": {
            "extends": "sugar.views.props.space",
            "description": "Specify the margin inline start (left)"
        },
        "inlineEnd": {
            "extends": "sugar.views.props.space",
            "description": "Specify the margin inline end (right)"
        }
    }
}
