{
    "metas": {
        "lang": "en",
        "title": "Plop",
        "description": "Hello world",
        "themeColor": "#FFBB00",
        "author": {
            "name": "Olivier Bossel",
            "email": "olivier.bossel@gmail.com",
            "url": "https://olivierbossel.com"
        },
        "og": {
            "title": "plop",
            "description": "wiufhweiufh wiuehfiuwehf",
            "type": "website",
            "url": "https://olivierbossel.com",
            "image": "/cool-image.jpg"
        }
    },
    "assets": {
        "js": {
            "dev": {
                "id": "dev",
                "type": "module",
                "defer": true,
                "src": "/dist/js/index.ts",
                "env": "development"
            },
            "module": {
                "id": "module",
                "type": "module",
                "defer": true,
                "src": "/dist/js/module.es.js",
                "env": "production"
            },
            "main": {
                "id": "main",
                "nomodule": true,
                "defer": true,
                "src": "/dist/js/index.iife.js",
                "env": "production"
            }
        },
        "css": {
            "main": {
                "id": "main",
                "defer": true,
                "src": "/dist/css/index.css"
            }
        },
        "html": {
            "manifest": {
                "id": "manifest",
                "src": "./dist/favicon/favicon.html"
            }
        }
    },
    "head": {}
}